{
  "storage_version": 1,
  "name": "lighting-485-16ch-ttl-1",
  "friendly_name": "TTL-16\u8def\u7167\u660e\u6a21\u5757",
  "comment": null,
  "esphome_version": "2025.12.4",
  "src_version": 1,
  "address": "lighting-485-16ch-ttl-1.local",
  "web_port": 80,
  "esp_platform": "ESP32C3",
  "build_path": "E:\\esphome\\.esphome\\build\\lighting-485-16ch-ttl-1",
  "firmware_bin_path": "E:\\esphome\\.esphome\\build\\lighting-485-16ch-ttl-1\\.pioenvs\\lighting-485-16ch-ttl-1\\firmware.bin",
  "loaded_integrations": [
    "api",
    "button",
    "captive_portal",
    "esp32",
    "esphome",
    "globals",
    "interval",
    "json",
    "logger",
    "md5",
    "mdns",
    "network",
    "number",
    "ota",
    "preferences",
    "safe_mode",
    "script",
    "sensor",
    "sha256",
    "socket",
    "switch",
    "template",
    "uart",
    "web_server",
    "web_server_base",
    "web_server_idf",
    "wifi",
    "wifi_signal"
  ],
  "loaded_platforms": [
    "button/template",
    "number/template",
    "ota/esphome",
    "ota/web_server",
    "sensor/wifi_signal",
    "switch/template"
  ],
  "no_mdns": false,
  "framework": "esp-idf",
  "core_platform": "esp32"
}
