{
  "storage_version": 1,
  "name": "ld2412-esp32-c3-0",
  "friendly_name": "LD2412-ESP32-C3-0",
  "comment": null,
  "esphome_version": "2025.12.4",
  "src_version": 1,
  "address": "ld2412-esp32-c3-0.local",
  "web_port": null,
  "esp_platform": "ESP32C3",
  "build_path": "E:\\esphome\\.esphome\\build\\ld2412-esp32-c3-0",
  "firmware_bin_path": "E:\\esphome\\.esphome\\build\\ld2412-esp32-c3-0\\.pioenvs\\ld2412-esp32-c3-0\\firmware.bin",
  "loaded_integrations": [
    "aht10",
    "analog_threshold",
    "api",
    "bh1750",
    "binary_sensor",
    "button",
    "captive_portal",
    "esp32",
    "esphome",
    "gpio",
    "i2c",
    "ld2412",
    "ld24xx",
    "logger",
    "md5",
    "mdns",
    "network",
    "number",
    "ota",
    "preferences",
    "remote_base",
    "remote_receiver",
    "remote_transmitter",
    "safe_mode",
    "select",
    "sensor",
    "sha256",
    "socket",
    "switch",
    "template",
    "text_sensor",
    "uart",
    "web_server",
    "web_server_base",
    "web_server_idf",
    "wifi",
    "wifi_info",
    "wifi_signal"
  ],
  "loaded_platforms": [
    "binary_sensor/analog_threshold",
    "binary_sensor/gpio",
    "binary_sensor/ld2412",
    "button/ld2412",
    "button/template",
    "number/ld2412",
    "ota/esphome",
    "ota/web_server",
    "select/ld2412",
    "sensor/aht10",
    "sensor/bh1750",
    "sensor/ld2412",
    "sensor/wifi_signal",
    "switch/ld2412",
    "text_sensor/ld2412",
    "text_sensor/wifi_info"
  ],
  "no_mdns": false,
  "framework": "esp-idf",
  "core_platform": "esp32"
}
