{
  "storage_version": 1,
  "name": "s3",
  "friendly_name": "S3",
  "comment": null,
  "esphome_version": "2025.12.4",
  "src_version": 1,
  "address": "s3.local",
  "web_port": null,
  "esp_platform": "ESP32S3",
  "build_path": "E:\\esphome\\.esphome\\build\\s3",
  "firmware_bin_path": "E:\\esphome\\.esphome\\build\\s3\\.pioenvs\\s3\\firmware.bin",
  "loaded_integrations": [
    "api",
    "binary_sensor",
    "button",
    "captive_portal",
    "esp32",
    "esphome",
    "external_components",
    "hlk_ld2402",
    "logger",
    "md5",
    "mdns",
    "network",
    "number",
    "ota",
    "preferences",
    "safe_mode",
    "select",
    "sensor",
    "sha256",
    "socket",
    "status_led",
    "template",
    "text_sensor",
    "uart",
    "web_server",
    "web_server_base",
    "web_server_idf",
    "wifi"
  ],
  "loaded_platforms": [
    "binary_sensor/hlk_ld2402",
    "button/template",
    "number/template",
    "ota/esphome",
    "ota/web_server",
    "select/template",
    "sensor/hlk_ld2402",
    "text_sensor/hlk_ld2402"
  ],
  "no_mdns": false,
  "framework": "esp-idf",
  "core_platform": "esp32"
}
